stacklog/__init__.py
stacklog/_time_formatters.py
stacklog/compat.py
stacklog-2.0.2.dist-info/AUTHORS.rst
stacklog-2.0.2.dist-info/LICENSE
stacklog-2.0.2.dist-info/METADATA
stacklog-2.0.2.dist-info/WHEEL
stacklog-2.0.2.dist-info/RECORD
