Metadata-Version: 2.1
Name: stacklog
Version: 2.0.2
Summary: Stack log messages
Home-page: https://github.com/micahjsmith/stacklog
License: MIT
Keywords: stacklog,logging
Author: Micah Smith
Author-email: micahjsmith@gmail.com
Requires-Python: >=3.8,<3.13
Classifier: Development Status :: 5 - Production/Stable
Classifier: Intended Audience :: Developers
Classifier: License :: OSI Approved :: MIT License
Classifier: Natural Language :: English
Classifier: Programming Language :: Python :: 3
Classifier: Programming Language :: Python :: 3.8
Classifier: Programming Language :: Python :: 3.9
Classifier: Programming Language :: Python :: 3.10
Classifier: Programming Language :: Python :: 3.11
Classifier: Programming Language :: Python :: 3.12
Requires-Dist: typing-extensions (>=4.12.0) ; python_version < "3.10"
Project-URL: Documentation, https://micahjsmith.github.io/stacklog/
Project-URL: Repository, https://github.com/micahjsmith/stacklog
